pydantic_xml/__init__.py
pydantic_xml/compat.py
pydantic_xml/config.py
pydantic_xml/element/__init__.py
pydantic_xml/element/element.py
pydantic_xml/element/native/__init__.py
pydantic_xml/element/native/lxml.py
pydantic_xml/element/native/std.py
pydantic_xml/element/utils.py
pydantic_xml/errors.py
pydantic_xml/fields.py
pydantic_xml/model.py
pydantic_xml/mypy.py
pydantic_xml/py.typed
pydantic_xml/serializers/__init__.py
pydantic_xml/serializers/factories/__init__.py
pydantic_xml/serializers/factories/call.py
pydantic_xml/serializers/factories/heterogeneous.py
pydantic_xml/serializers/factories/homogeneous.py
pydantic_xml/serializers/factories/is_instance.py
pydantic_xml/serializers/factories/mapping.py
pydantic_xml/serializers/factories/model.py
pydantic_xml/serializers/factories/named_tuple.py
pydantic_xml/serializers/factories/primitive.py
pydantic_xml/serializers/factories/raw.py
pydantic_xml/serializers/factories/tagged_union.py
pydantic_xml/serializers/factories/tuple.py
pydantic_xml/serializers/factories/typed_mapping.py
pydantic_xml/serializers/factories/union.py
pydantic_xml/serializers/factories/wrapper.py
pydantic_xml/serializers/serializer.py
pydantic_xml/typedefs.py
pydantic_xml/utils.py
pydantic_xml-2.18.0.dist-info/METADATA
pydantic_xml-2.18.0.dist-info/WHEEL
pydantic_xml-2.18.0.dist-info/licenses/LICENSE
pydantic_xml-2.18.0.dist-info/RECORD
