Metadata-Version: 2.4
Name: pydantic-xml
Version: 2.18.0
Summary: pydantic xml extension
License: Unlicense
License-File: LICENSE
Keywords: pydantic,xml,serialization,deserialization,lxml
Author: Dmitry Pershin
Author-email: dapper1291@gmail.com
Requires-Python: >=3.8
Classifier: Development Status :: 5 - Production/Stable
Classifier: Framework :: Pydantic
Classifier: Framework :: Pydantic :: 1
Classifier: Framework :: Pydantic :: 2
Classifier: Intended Audience :: Developers
Classifier: License :: OSI Approved
Classifier: License :: Public Domain
Classifier: Natural Language :: English
Classifier: Operating System :: OS Independent
Classifier: Programming Language :: Python
Classifier: Programming Language :: Python :: 3
Classifier: Programming Language :: Python :: 3.8
Classifier: Programming Language :: Python :: 3.9
Classifier: Programming Language :: Python :: 3.10
Classifier: Programming Language :: Python :: 3.11
Classifier: Programming Language :: Python :: 3.12
Classifier: Programming Language :: Python :: 3.13
Classifier: Programming Language :: Python :: 3.14
Classifier: Topic :: Software Development :: Libraries
Classifier: Topic :: Text Processing :: Markup :: XML
Classifier: Typing :: Typed
Provides-Extra: docs
Provides-Extra: lxml
Requires-Dist: Sphinx (>=5.3.0,<6.0.0) ; extra == "docs"
Requires-Dist: furo (>=2022.12.7,<2023.0.0) ; extra == "docs"
Requires-Dist: lxml (>=4.9.0) ; extra == "lxml"
Requires-Dist: pydantic (>=2.6.0,!=2.10.0b1)
Requires-Dist: pydantic-core (>=2.15.0)
Requires-Dist: sphinx-copybutton (>=0.5.1,<0.6.0) ; extra == "docs"
Requires-Dist: sphinx_design (>=0.3.0,<0.4.0) ; extra == "docs"
Requires-Dist: toml (>=0.10.2,<0.11.0) ; extra == "docs"
Project-URL: Documentation, https://pydantic-xml.readthedocs.io
Project-URL: Homepage, https://github.com/dapper91/pydantic-xml
Project-URL: Repository, https://github.com/dapper91/pydantic-xml
